odoo/addons/mrp_component_operation/README.rst
odoo/addons/mrp_component_operation/__init__.py
odoo/addons/mrp_component_operation/__manifest__.py
odoo/addons/mrp_component_operation/i18n/es.po
odoo/addons/mrp_component_operation/i18n/it.po
odoo/addons/mrp_component_operation/i18n/mrp_component_operation.pot
odoo/addons/mrp_component_operation/models/__init__.py
odoo/addons/mrp_component_operation/models/mrp_component_operation.py
odoo/addons/mrp_component_operation/models/mrp_production.py
odoo/addons/mrp_component_operation/models/stock_location_route.py
odoo/addons/mrp_component_operation/readme/CONTRIBUTORS.rst
odoo/addons/mrp_component_operation/readme/DESCRIPTION.rst
odoo/addons/mrp_component_operation/readme/USAGE.rst
odoo/addons/mrp_component_operation/security/ir.model.access.csv
odoo/addons/mrp_component_operation/static/description/icon.png
odoo/addons/mrp_component_operation/static/description/index.html
odoo/addons/mrp_component_operation/tests/__init__.py
odoo/addons/mrp_component_operation/tests/test_component_operate.py
odoo/addons/mrp_component_operation/views/mrp_component_operation_views.xml
odoo/addons/mrp_component_operation/views/mrp_production_views.xml
odoo/addons/mrp_component_operation/views/stock_view.xml
odoo/addons/mrp_component_operation/wizards/__init__.py
odoo/addons/mrp_component_operation/wizards/mrp_component_operate.py
odoo/addons/mrp_component_operation/wizards/mrp_component_operate_wizard.xml
odoo14_addon_mrp_component_operation-14.0.1.2.0.dist-info/METADATA
odoo14_addon_mrp_component_operation-14.0.1.2.0.dist-info/WHEEL
odoo14_addon_mrp_component_operation-14.0.1.2.0.dist-info/top_level.txt
odoo14_addon_mrp_component_operation-14.0.1.2.0.dist-info/RECORD
