Metadata-Version: 2.1
Name: odoo14-addon-mrp_component_operation
Version: 14.0.1.2.0
Summary: Allows to operate the components from a MO
Home-page: https://github.com/OCA/manufacture
Author: ForgeFlow, Odoo Community Association (OCA)
Author-email: support@odoo-community.org
License: LGPL-3
Classifier: Programming Language :: Python
Classifier: Framework :: Odoo
Classifier: Framework :: Odoo :: 14.0
Classifier: License :: OSI Approved :: GNU Lesser General Public License v3 (LGPLv3)
Requires-Python: >=3.6
Requires-Dist: odoo14-addon-stock-move-forced-lot
Requires-Dist: odoo <14.1dev,>=14.0a
